CHANGES.rst
MANIFEST.in
README.rst
setup.cfg
setup.py
streamio/__init__.py
streamio/__init__.pyc
streamio/sort.py
streamio/sort.pyc
streamio/stat.py
streamio/stat.pyc
streamio/stream.py
streamio/stream.pyc
streamio/version.py
streamio/version.pyc
streamio.egg-info/PKG-INFO
streamio.egg-info/SOURCES.txt
streamio.egg-info/dependency_links.txt
streamio.egg-info/entry_points.txt
streamio.egg-info/requires.txt
streamio.egg-info/top_level.txt
streamio.egg-info/zip-safe