Metadata-Version: 1.1
Name: streamio
Version: 0.0.7
Summary: reading, writing and sorting large files
Home-page: https://bitbucket.org/prologic/streamio
Author: James Mills
Author-email: James Mills, j dot mills at griffith dot edu dot au
License: MIT
Download-URL: https://bitbucket.org/prologic/streamio/downloads/
Keywords: Python Large Files Reading Writing Sorting Streaming
Platform: POSIX
Classifier: Development Status :: 4 - Beta
Classifier: Environment :: Console
Classifier: Intended Audience :: Developers
Classifier: License :: OSI Approved :: MIT License
Classifier: Natural Language :: English
Classifier: Operating System :: MacOS :: MacOS X
Classifier: Operating System :: POSIX :: Linux
Classifier: Programming Language :: Python :: 2.7
